etao_langchain/__init__.py
etao_langchain/text_splitter.py
etao_langchain/agents/__init__.py
etao_langchain/agents/chatglm_functions_agent/__init__.py
etao_langchain/agents/chatglm_functions_agent/base.py
etao_langchain/agents/chatglm_functions_agent/output_parser.py
etao_langchain/agents/chatglm_functions_agent/prompt.py
etao_langchain/agents/llm_functions_agent/__init__.py
etao_langchain/agents/llm_functions_agent/base.py
etao_langchain/autogen_role/__init__.py
etao_langchain/autogen_role/assistant.py
etao_langchain/autogen_role/custom.py
etao_langchain/autogen_role/groupchat_manager.py
etao_langchain/autogen_role/user.py
etao_langchain/chains/__init__.py
etao_langchain/chains/loader_output.py
etao_langchain/chains/transform.py
etao_langchain/chains/autogen/__init__.py
etao_langchain/chains/autogen/auto_gen.py
etao_langchain/chains/combine_documents/__init__.py
etao_langchain/chains/combine_documents/stuff.py
etao_langchain/chains/conversational_retrieval/__init__.py
etao_langchain/chains/conversational_retrieval/base.py
etao_langchain/chains/question_answering/__init__.py
etao_langchain/chains/retrieval/__init__.py
etao_langchain/chains/retrieval/retrieval_chain.py
etao_langchain/chains/router/__init__.py
etao_langchain/chains/router/multi_rule.py
etao_langchain/chains/router/rule_router.py
etao_langchain/chat_models/__init__.py
etao_langchain/chat_models/host_llm.py
etao_langchain/chat_models/minimax.py
etao_langchain/chat_models/proxy_llm.py
etao_langchain/chat_models/qwen.py
etao_langchain/chat_models/sensetime.py
etao_langchain/chat_models/wenxin.py
etao_langchain/chat_models/xunfeiai.py
etao_langchain/chat_models/zhipuai.py
etao_langchain/chat_models/interface/__init__.py
etao_langchain/chat_models/interface/minimax.py
etao_langchain/chat_models/interface/openai.py
etao_langchain/chat_models/interface/types.py
etao_langchain/chat_models/interface/utils.py
etao_langchain/chat_models/interface/wenxin.py
etao_langchain/chat_models/interface/xunfei.py
etao_langchain-0.1.12.dist-info/LICENSE
etao_langchain-0.1.12.dist-info/METADATA
etao_langchain-0.1.12.dist-info/WHEEL
etao_langchain-0.1.12.dist-info/top_level.txt
etao_langchain-0.1.12.dist-info/RECORD
