Metadata-Version: 2.1
Name: etao_langchain
Version: 0.1.12
Summary: etao langchain
Home-page: 
Author: HaiLong Zheng
Author-email: xxxx@gmail.com
License: MIT
Classifier: License :: OSI Approved :: MIT License
Classifier: Programming Language :: Python
Classifier: Programming Language :: Python :: 3
Classifier: Programming Language :: Python :: 3.6
Classifier: Programming Language :: Python :: Implementation :: CPython
Classifier: Programming Language :: Python :: Implementation :: PyPy
Requires-Python: >=3.10.0
License-File: LICENSE
